photobooth/__init__.py
photobooth/__main__.py
photobooth/appconfig.py
photobooth/application.py
photobooth/container.py
photobooth/database/alembic/env.py
photobooth/database/alembic/script.py.mako
photobooth/database/alembic/versions/24456e322528_add_captured_original_to_mediaitem.py
photobooth/database/alembic/versions/7e0d6dfb1b1d_initial_schema.py
photobooth/database/database.py
photobooth/database/models.py
photobooth/database/schemas.py
photobooth/database/types.py
photobooth/demoassets/userdata/backgrounds/background.jpg
photobooth/demoassets/userdata/backgrounds/pink-7761356_1920.jpg
photobooth/demoassets/userdata/fonts/Roboto-Bold-LICENSE.txt
photobooth/demoassets/userdata/fonts/Roboto-Bold.ttf
photobooth/demoassets/userdata/frames/frame_image_photobooth-app.png
photobooth/demoassets/userdata/frames/pixabay-poster-2871536_1920.png
photobooth/demoassets/userdata/predefined_images/photobooth-collage-predefined-image.png
photobooth/demoassets/userdata/predefined_images/photobooth-gif-animation-predefined-image.png
photobooth/models/genericstats.py
photobooth/plugins/__init__.py
photobooth/plugins/base_plugin.py
photobooth/plugins/commander/__init__.py
photobooth/plugins/commander/commander.py
photobooth/plugins/commander/config.py
photobooth/plugins/commander/models.py
photobooth/plugins/filter_pilgram2/__init__.py
photobooth/plugins/filter_pilgram2/config.py
photobooth/plugins/filter_pilgram2/filter_pilgram2.py
photobooth/plugins/gpio_lights/__init__.py
photobooth/plugins/gpio_lights/config.py
photobooth/plugins/gpio_lights/gpio_lights.py
photobooth/plugins/synchronizer_legacy/__init__.py
photobooth/plugins/synchronizer_legacy/config.py
photobooth/plugins/synchronizer_legacy/connectors/__init__.py
photobooth/plugins/synchronizer_legacy/connectors/abstractconnector.py
photobooth/plugins/synchronizer_legacy/connectors/connector_factory.py
photobooth/plugins/synchronizer_legacy/connectors/filesystem.py
photobooth/plugins/synchronizer_legacy/connectors/ftp.py
photobooth_app-8.7.0.dist-info/WHEEL
photobooth_app-8.7.0.dist-info/entry_points.txt
photobooth_app-8.7.0.dist-info/METADATA
photobooth_app-8.7.0.dist-info/RECORD
