Metadata-Version: 2.3
Name: photobooth-app
Version: 8.7.0
Summary: Photobooth app written in Python supporting DSLR, picamera2 and webcameras
Keywords: photobooth,photobooth-app,wedding,booth,raspberry-pi,camera,python,filter,gphoto2,dslr,picamera2
Author: Michael G
Author-email: Michael G <me@mgineer85.de>
License: MIT
Classifier: License :: OSI Approved :: MIT License
Classifier: Operating System :: OS Independent
Classifier: Programming Language :: Python :: 3
Classifier: Programming Language :: Python :: 3.11
Classifier: Programming Language :: Python :: 3.12
Classifier: Programming Language :: Python :: 3.13
Classifier: Programming Language :: Python :: 3.14
Classifier: Topic :: Multimedia :: Graphics
Classifier: Topic :: Software Development :: Libraries :: Python Modules
Classifier: Topic :: Multimedia :: Graphics :: Capture :: Digital Camera
Requires-Dist: fastapi>=0.106.0
Requires-Dist: opencv-python-headless~=4.13.0
Requires-Dist: numpy>=2.0.0
Requires-Dist: pillow>=12.1.0
Requires-Dist: psutil>=7.2.0
Requires-Dist: pydantic>=2.11.2
Requires-Dist: pydantic-extra-types>=2.3.0
Requires-Dist: pydantic-settings>=2.11,<2.13
Requires-Dist: sse-starlette>=2.2.0,<4.0.0
Requires-Dist: uvicorn[standard]>=0.24
Requires-Dist: python-dotenv>=1.0.0
Requires-Dist: pyserial~=3.5
Requires-Dist: jsonref>=1.1.0
Requires-Dist: pilgram2>=2.0.6
Requires-Dist: linuxpy>=0.10.0 ; sys_platform == 'linux'
Requires-Dist: gpiozero~=2.0.0
Requires-Dist: gphoto2>=2.6.1,<2.7 ; sys_platform == 'darwin' or sys_platform == 'linux'
Requires-Dist: python-statemachine>=2.4.0
Requires-Dist: python-multipart>=0.0.6
Requires-Dist: pyjwt[crypto]>=2.8.0
Requires-Dist: piexif>=1.1.3
Requires-Dist: sqlalchemy>=2.0.37
Requires-Dist: simplejpeg>=1.8.2
Requires-Dist: pyturbojpeg>=1.7.0
Requires-Dist: pluggy>=1.5.0
Requires-Dist: av>=16.0,<16.2
Requires-Dist: alembic>=1.15.2
Requires-Dist: onnxruntime
Requires-Dist: rclone-bin-api==1.0.2
Requires-Dist: nc-py-api>=0.20.1
Requires-Dist: wigglecam
Requires-Dist: pynng
Requires-Dist: niquests>=3.15.0
Maintainer: Michael G
Maintainer-email: Michael G <me@mgineer85.de>
Requires-Python: >=3.11
Project-URL: Homepage, https://github.com/photobooth-app/photobooth-app
Project-URL: Repository, https://github.com/photobooth-app/photobooth-app
Project-URL: Documentation, https://photobooth-app.org
